endex_factset_events_and_transcripts/__init__.py
endex_factset_events_and_transcripts/_base_client.py
endex_factset_events_and_transcripts/_client.py
endex_factset_events_and_transcripts/_compat.py
endex_factset_events_and_transcripts/_constants.py
endex_factset_events_and_transcripts/_exceptions.py
endex_factset_events_and_transcripts/_files.py
endex_factset_events_and_transcripts/_models.py
endex_factset_events_and_transcripts/_qs.py
endex_factset_events_and_transcripts/_resource.py
endex_factset_events_and_transcripts/_response.py
endex_factset_events_and_transcripts/_streaming.py
endex_factset_events_and_transcripts/_types.py
endex_factset_events_and_transcripts/_version.py
endex_factset_events_and_transcripts/py.typed
endex_factset_events_and_transcripts/_utils/__init__.py
endex_factset_events_and_transcripts/_utils/_logs.py
endex_factset_events_and_transcripts/_utils/_proxy.py
endex_factset_events_and_transcripts/_utils/_reflection.py
endex_factset_events_and_transcripts/_utils/_streams.py
endex_factset_events_and_transcripts/_utils/_sync.py
endex_factset_events_and_transcripts/_utils/_transform.py
endex_factset_events_and_transcripts/_utils/_typing.py
endex_factset_events_and_transcripts/_utils/_utils.py
endex_factset_events_and_transcripts/lib/.keep
endex_factset_events_and_transcripts/resources/__init__.py
endex_factset_events_and_transcripts/resources/calendar_events.py
endex_factset_events_and_transcripts/resources/events_audio/__init__.py
endex_factset_events_and_transcripts/resources/events_audio/by_date.py
endex_factset_events_and_transcripts/resources/events_audio/by_file_name.py
endex_factset_events_and_transcripts/resources/events_audio/by_ids.py
endex_factset_events_and_transcripts/resources/events_audio/by_upload_time.py
endex_factset_events_and_transcripts/resources/events_audio/events_audio.py
endex_factset_events_and_transcripts/resources/events_audio/history.py
endex_factset_events_and_transcripts-0.1.0a1.dist-info/METADATA
endex_factset_events_and_transcripts-0.1.0a1.dist-info/WHEEL
endex_factset_events_and_transcripts-0.1.0a1.dist-info/licenses/LICENSE
endex_factset_events_and_transcripts-0.1.0a1.dist-info/RECORD
